isilon_hadoop_tools/__init__.py
isilon_hadoop_tools/_scripts.py
isilon_hadoop_tools/cli.py
isilon_hadoop_tools/directories.py
isilon_hadoop_tools/identities.py
isilon_hadoop_tools/onefs.py
isilon_hadoop_tools-5.0.1.dist-info/LICENSE
isilon_hadoop_tools-5.0.1.dist-info/METADATA
isilon_hadoop_tools-5.0.1.dist-info/WHEEL
isilon_hadoop_tools-5.0.1.dist-info/entry_points.txt
isilon_hadoop_tools-5.0.1.dist-info/top_level.txt
isilon_hadoop_tools-5.0.1.dist-info/RECORD
