Metadata-Version: 2.1
Name: isilon-hadoop-tools
Version: 5.0.1
Summary: Tools for Using Hadoop with OneFS
Home-page: https://github.com/isilon/isilon_hadoop_tools
Maintainer: Isilon
Maintainer-email: support@isilon.com
License: MIT
Classifier: Development Status :: 5 - Production/Stable
Classifier: License :: OSI Approved :: MIT License
Classifier: Programming Language :: Python :: 3
Classifier: Programming Language :: Python :: 3.7
Classifier: Programming Language :: Python :: 3.8
Classifier: Programming Language :: Python :: 3.9
Classifier: Programming Language :: Python :: 3.10
Classifier: Programming Language :: Python :: 3.11
Requires-Python: >=3.7
License-File: LICENSE
Requires-Dist: isi-sdk-7-2 (~=0.2.11)
Requires-Dist: isi-sdk-8-0 (~=0.2.11)
Requires-Dist: isi-sdk-8-0-1 (~=0.2.11)
Requires-Dist: isi-sdk-8-1-0 (~=0.2.11)
Requires-Dist: isi-sdk-8-1-1 (~=0.2.11)
Requires-Dist: isi-sdk-8-2-0 (~=0.2.11)
Requires-Dist: isi-sdk-8-2-1 (~=0.2.11)
Requires-Dist: isi-sdk-8-2-2 (~=0.2.11)
Requires-Dist: requests (>=2.20.0)
Requires-Dist: setuptools (>=41.0.0)
Requires-Dist: urllib3 (>=1.22.0)
